cn_workdays/README.md
cn_workdays/VERSION
cn_workdays/__init__.py
cn_workdays/__version__.py
cn_workdays/cli.py
cn_workdays/config.json
cn_workdays/holiparse/holiparse_marimo.py
cn_workdays/holiparse/parser.py
cn_workdays/workcalc/calculator.py
cn_workdays/workcalc/calculator.tcss
cn_workdays/workcalc/workcalc_marimo.py
cn_workdays/workcalc/workcalc_textual.py
cn_workdays/workcalc_terminal.png
cnworkdays-2026.0.dist-info/METADATA
cnworkdays-2026.0.dist-info/WHEEL
cnworkdays-2026.0.dist-info/entry_points.txt
cnworkdays-2026.0.dist-info/RECORD
