Metadata-Version: 2.1
Name: cnworkdays
Version: 2026.0
Summary: A Python tool for managing Chinese public holidays and compensatory working days. This tool helps you accurately calculate working days while accounting for China's unique holiday schedule.
Author-Email: Aolin <aolinz@outlook.com>
Requires-Python: <4.0,>=3.9
Requires-Dist: marimo<1.0.0,>=0.6.23
Requires-Dist: icalendar>=5.0.13
Requires-Dist: rich>=13.9.4
Requires-Dist: hypercorn>=0.17.3
Requires-Dist: textual>=1.0.0
